lhcoptics/__init__.py
lhcoptics/aperture.py
lhcoptics/arcs.py
lhcoptics/circuits.py
lhcoptics/ir1.py
lhcoptics/ir2.py
lhcoptics/ir3.py
lhcoptics/ir4.py
lhcoptics/ir5.py
lhcoptics/ir6.py
lhcoptics/ir7.py
lhcoptics/ir8.py
lhcoptics/irs.py
lhcoptics/knob.py
lhcoptics/lsa_util.py
lhcoptics/model_madx.py
lhcoptics/model_xsuite.py
lhcoptics/nxcals_util.py
lhcoptics/optics.py
lhcoptics/opttable.py
lhcoptics/rdmsignal.py
lhcoptics/repo.py
lhcoptics/section.py
lhcoptics/utils.py
lhcoptics-0.0.3.dist-info/METADATA
lhcoptics-0.0.3.dist-info/WHEEL
lhcoptics-0.0.3.dist-info/top_level.txt
lhcoptics-0.0.3.dist-info/RECORD
